pcmflux/__init__.py
pcmflux/audio_capture_module.so
pcmflux.libs/libFLAC-c7cf90bd.so.8.3.0
pcmflux.libs/libX11-xcb-3de3ce09.so.1.0.0
pcmflux.libs/libXau-7926f62a.so.6.0.0
pcmflux.libs/libXi-a0a2b9be.so.6.1.0
pcmflux.libs/libXtst-ffe24c4a.so.6.1.0
pcmflux.libs/libasyncns-d605b037.so.0.3.1
pcmflux.libs/libblkid-e4a77f31.so.1.1.0
pcmflux.libs/libcap-f91f74e2.so.2.48
pcmflux.libs/libdbus-1-2e96ff72.so.3.19.7
pcmflux.libs/libgcrypt-4af81264.so.20.2.5
pcmflux.libs/libgpg-error-6019f251.so.0.24.2
pcmflux.libs/libgsm-f480b0fa.so.1.0.17
pcmflux.libs/liblz4-b2322fcc.so.1.8.3
pcmflux.libs/liblzma-6f9d2abe.so.5.2.4
pcmflux.libs/libmount-bbb803f3.so.1.1.0
pcmflux.libs/libogg-38327173.so.0.8.2
pcmflux.libs/libopus-962cd6a3.so.0.6.1
pcmflux.libs/libpcre2-8-8701a61e.so.0.7.1
pcmflux.libs/libpulse-49ab7b7d.so.0.23.0
pcmflux.libs/libpulse-simple-28e523c7.so.0.1.1
pcmflux.libs/libpulsecommon-14-09cbfe09.0.so
pcmflux.libs/libselinux-5700a1fd.so.1
pcmflux.libs/libsndfile-e085dfbe.so.1.0.28
pcmflux.libs/libsystemd-b2a15c2d.so.0.23.0
pcmflux.libs/libuuid-8d96e403.so.1.3.0
pcmflux.libs/libvorbis-a0237a76.so.0.4.8
pcmflux.libs/libvorbisenc-08e46846.so.2.0.11
pcmflux.libs/libxcb-8fcfc57e.so.1.1.0
pcmflux-1.0.6.dist-info/METADATA
pcmflux-1.0.6.dist-info/WHEEL
pcmflux-1.0.6.dist-info/top_level.txt
pcmflux-1.0.6.dist-info/RECORD
pcmflux-1.0.6.dist-info/licenses/LICENSE
pcmflux-1.0.6.dist-info/sboms/auditwheel.cdx.json
