Metadata-Version: 2.4
Name: pcmflux
Version: 1.0.6
Summary: A performant audio capture pipeline that encodes raw PCM to Opus, skipping silence.
Home-page: https://github.com/linuxserver/pcmflux
Author: Linuxserver.io
Author-email: pypi@linuxserver.io
License: MPL-2.0
Classifier: Programming Language :: Python :: 3
Classifier: Operating System :: POSIX :: Linux
Requires-Python: >=3.6
License-File: LICENSE
Dynamic: author
Dynamic: author-email
Dynamic: classifier
Dynamic: description
Dynamic: description-content-type
Dynamic: home-page
Dynamic: license
Dynamic: license-file
Dynamic: requires-python
Dynamic: summary
